bigan_trading/__init__.py
bigan_trading/trading.py
bigan_trading-0.0.1.dist-info/METADATA
bigan_trading-0.0.1.dist-info/WHEEL
bigan_trading-0.0.1.dist-info/top_level.txt
bigan_trading-0.0.1.dist-info/RECORD
