Metadata-Version: 2.1
Name: bigan-trading
Version: 0.0.1
Summary: Bigan Trading Package
Home-page: https://dev.azure.com/FutureFantasy/BiGan/_git/bigan-trading
Author: heian0224
Author-email: heian0224@gmail.com
License: UNKNOWN
Project-URL: Bug Tracker, https://dev.azure.com/FutureFantasy/BiGan/_git/bigan-trading/issues
Platform: UNKNOWN
Classifier: Programming Language :: Python :: 3
Classifier: License :: OSI Approved :: MIT License
Classifier: Operating System :: OS Independent
Requires-Python: >=3.10
